{
    "type": "FeatureCollection",
    "features": [
        {
            "type": "Feature",
            "properties": {
                "MOVEMENT_ID": "1",
                "TRACTCE": "023315",
                "GEOID": "13089023315",
                "DISPLAY_NAME": "Census Tract 233.15"
            },
            "geometry": {
                "type": "Polygon",
                "coordinates": [
                    [
                        [
                            -84.108219,
                            33.758834
                        ],
                        [
                            -84.108185,
                            33.759568
                        ],
                        [
                            -84.108132,
                            33.76022
                        ],
                        [
                            -84.108074,
                            33.760437
                        ],
                        [
                            -84.107969,
                            33.760778
                        ],
                        [
                            -84.107946,
                            33.760832
                        ],
                        [
                            -84.107931,
                            33.760914
                        ],
                        [
                            -84.107911,
                            33.760944
                        ],
                        [
                            -84.107883,
                            33.761055
                        ],
                        [
                            -84.107898,
                            33.761129
                        ],
                        [
                            -84.107728,
                            33.76119
                        ],
                        [
                            -84.107337,
                            33.761357
                        ],
                        [
                            -84.107131,
                            33.761462
                        ],
                        [
                            -84.107019,
                            33.761541
                        ],
                        [
                            -84.106959,
                            33.761578
                        ],
                        [
                            -84.106831,
                            33.76167
                        ],
                        [
                            -84.106737,
                            33.761762
                        ],
                        [
                            -84.106717,
                            33.761773
                        ],
                        [
                            -84.106698,
                            33.761793
                        ],
                        [
                            -84.106568,
                            33.761908
                        ],
                        [
                            -84.106404,
                            33.762071
                        ],
                        [
                            -84.106264,
                            33.762255
                        ],
                        [
                            -84.106094,
                            33.762543
                        ],
                        [
                            -84.105332,
                            33.764302
                        ],
                        [
                            -84.105329,
                            33.76432
                        ],
                        [
                            -84.10517,
                            33.764756
                        ],
                        [
                            -84.105131,
                            33.764826
                        ],
                        [
                            -84.104922,
                            33.765244
                        ],
                        [
                            -84.104621,
                            33.765627
                        ],
                        [
                            -84.10394,
                            33.766177
                        ],
                        [
                            -84.103385,
                            33.766641
                        ],
                        [
                            -84.10325,
                            33.766779
                        ],
                        [
                            -84.102361,
                            33.767494
                        ],
                        [
                            -84.102101,
                            33.767598
                        ],
                        [
                            -84.101651,
                            33.767757
                        ],
                        [
                            -84.10121,
                            33.767922
                        ],
                        [
                            -84.10079,
                            33.768099
                        ],
                        [
                            -84.100728,
                            33.768078
                        ],
                        [
                            -84.100211,
                            33.767942
                        ],
                        [
                            -84.099639,
                            33.767825
                        ],
                        [
                            -84.099112,
                            33.767728
                        ],
                        [
                            -84.098857,
                            33.76767
                        ],
                        [
                            -84.098247,
                            33.767515
                        ],
                        [
                            -84.097641,
                            33.767248
                        ],
                        [
                            -84.096901,
                            33.767009
                        ],
                        [
                            -84.096309,
                            33.766794
                        ],
                        [
                            -84.095754,
                            33.766625
                        ],
                        [
                            -84.095406,
                            33.766538
                        ],
                        [
                            -84.095251,
                            33.766522
                        ],
                        [
                            -84.094951,
                            33.766451
                        ],
                        [
                            -84.094467,
                            33.766368
                        ],
                        [
                            -84.094128,
                            33.766329
                        ],
                        [
                            -84.094132,
                            33.766481
                        ],
                        [
                            -84.094121,
                            33.766597
                        ],
                        [
                            -84.094026,
                            33.766989
                        ],
                        [
                            -84.093963,
                            33.767228
                        ],
                        [
                            -84.093895,
                            33.767383
                        ],
                        [
                            -84.093684,
                            33.767404
                        ],
                        [
                            -84.091368,
                            33.767359
                        ],
                        [
                            -84.090271,
                            33.76732
                        ],
                        [
                            -84.088491,
                            33.767346
                        ],
                        [
                            -84.084162,
                            33.767263
                        ],
                        [
                            -84.079457,
                            33.767313
                        ],
                        [
                            -84.079102,
                            33.767313
                        ],
                        [
                            -84.077954,
                            33.76725
                        ],
                        [
                            -84.077831,
                            33.767561
                        ],
                        [
                            -84.077779,
                            33.7678
                        ],
                        [
                            -84.077721,
                            33.768052
                        ],
                        [
                            -84.077676,
                            33.768304
                        ],
                        [
                            -84.077663,
                            33.76853
                        ],
                        [
                            -84.077683,
                            33.76874
                        ],
                        [
                            -84.077734,
                            33.768969
                        ],
                        [
                            -84.078044,
                            33.77019
                        ],
                        [
                            -84.078083,
                            33.770422
                        ],
                        [
                            -84.078102,
                            33.770655
                        ],
                        [
                            -84.078109,
                            33.770881
                        ],
                        [
                            -84.078096,
                            33.771094
                        ],
                        [
                            -84.07807,
                            33.771307
                        ],
                        [
                            -84.078038,
                            33.771443
                        ],
                        [
                            -84.07796,
                            33.771695
                        ],
                        [
                            -84.077857,
                            33.77196
                        ],
                        [
                            -84.077676,
                            33.77225
                        ],
                        [
                            -84.07752,
                            33.772493
                        ],
                        [
                            -84.076895,
                            33.773275
                        ],
                        [
                            -84.076832,
                            33.773351
                        ],
                        [
                            -84.076072,
                            33.774192
                        ],
                        [
                            -84.07592,
                            33.774355
                        ],
                        [
                            -84.075647,
                            33.774501
                        ],
                        [
                            -84.075063,
                            33.77477
                        ],
                        [
                            -84.074753,
                            33.774876
                        ],
                        [
                            -84.07437,
                            33.774972
                        ],
                        [
                            -84.07418,
                            33.775009
                        ],
                        [
                            -84.073889,
                            33.775013
                        ],
                        [
                            -84.07328,
                            33.775043
                        ],
                        [
                            -84.072891,
                            33.775001
                        ],
                        [
                            -84.072777,
                            33.774975
                        ],
                        [
                            -84.072515,
                            33.774906
                        ],
                        [
                            -84.072029,
                            33.774752
                        ],
                        [
                            -84.071539,
                            33.774554
                        ],
                        [
                            -84.070949,
                            33.774334
                        ],
                        [
                            -84.069725,
                            33.773864
                        ],
                        [
                            -84.069202,
                            33.773652
                        ],
                        [
                            -84.068522,
                            33.773394
                        ],
                        [
                            -84.067291,
                            33.77292
                        ],
                        [
                            -84.06687,
                            33.772753
                        ],
                        [
                            -84.066549,
                            33.772618
                        ],
                        [
                            -84.066201,
                            33.772493
                        ],
                        [
                            -84.065824,
                            33.772366
                        ],
                        [
                            -84.064621,
                            33.772158
                        ],
                        [
                            -84.064085,
                            33.772124
                        ],
                        [
                            -84.063679,
                            33.772135
                        ],
                        [
                            -84.063318,
                            33.772166
                        ],
                        [
                            -84.062938,
                            33.772206
                        ],
                        [
                            -84.061637,
                            33.772356
                        ],
                        [
                            -84.061154,
                            33.7724
                        ],
                        [
                            -84.060005,
                            33.772539
                        ],
                        [
                            -84.058612,
                            33.772693
                        ],
                        [
                            -84.058192,
                            33.772729
                        ],
                        [
                            -84.058111,
                            33.772722
                        ],
                        [
                            -84.058021,
                            33.772677
                        ],
                        [
                            -84.057871,
                            33.772574
                        ],
                        [
                            -84.057825,
                            33.772539
                        ],
                        [
                            -84.054814,
                            33.770207
                        ],
                        [
                            -84.053315,
                            33.768009
                        ],
                        [
                            -84.052115,
                            33.766708
                        ],
                        [
                            -84.051972,
                            33.766627
                        ],
                        [
                            -84.049613,
                            33.765307
                        ],
                        [
                            -84.048613,
                            33.765607
                        ],
                        [
                            -84.047186,
                            33.765091
                        ],
                        [
                            -84.046211,
                            33.764506
                        ],
                        [
                            -84.043313,
                            33.762307
                        ],
                        [
                            -84.043213,
                            33.761507
                        ],
                        [
                            -84.043117,
                            33.76101
                        ],
                        [
                            -84.042113,
                            33.760108
                        ],
                        [
                            -84.041647,
                            33.759271
                        ],
                        [
                            -84.041613,
                            33.759208
                        ],
                        [
                            -84.040313,
                            33.757708
                        ],
                        [
                            -84.038413,
                            33.757408
                        ],
                        [
                            -84.038215,
                            33.757804
                        ],
                        [
                            -84.034585,
                            33.756746
                        ],
                        [
                            -84.032413,
                            33.756108
                        ],
                        [
                            -84.03072,
                            33.755112
                        ],
                        [
                            -84.026413,
                            33.753108
                        ],
                        [
                            -84.023713,
                            33.752808
                        ],
                        [
                            -84.027305,
                            33.749989
                        ],
                        [
                            -84.030178,
                            33.747795
                        ],
                        [
                            -84.035754,
                            33.743584
                        ],
                        [
                            -84.037265,
                            33.742481
                        ],
                        [
                            -84.04123,
                            33.739455
                        ],
                        [
                            -84.042751,
                            33.737992
                        ],
                        [
                            -84.043887,
                            33.736955
                        ],
                        [
                            -84.045378,
                            33.735547
                        ],
                        [
                            -84.045528,
                            33.735411
                        ],
                        [
                            -84.045686,
                            33.735288
                        ],
                        [
                            -84.045852,
                            33.735174
                        ],
                        [
                            -84.046027,
                            33.735067
                        ],
                        [
                            -84.046208,
                            33.73497
                        ],
                        [
                            -84.04653,
                            33.734828
                        ],
                        [
                            -84.046865,
                            33.734713
                        ],
                        [
                            -84.047037,
                            33.734664
                        ],
                        [
                            -84.048069,
                            33.734502
                        ],
                        [
                            -84.048574,
                            33.73444
                        ],
                        [
                            -84.048965,
                            33.734403
                        ],
                        [
                            -84.049211,
                            33.73439
                        ],
                        [
                            -84.049546,
                            33.734379
                        ],
                        [
                            -84.050205,
                            33.734376
                        ],
                        [
                            -84.052066,
                            33.73443
                        ],
                        [
                            -84.056093,
                            33.734452
                        ],
                        [
                            -84.058045,
                            33.734475
                        ],
                        [
                            -84.05826,
                            33.734481
                        ],
                        [
                            -84.058583,
                            33.734472
                        ],
                        [
                            -84.058905,
                            33.734442
                        ],
                        [
                            -84.059117,
                            33.734409
                        ],
                        [
                            -84.059327,
                            33.734368
                        ],
                        [
                            -84.059534,
                            33.734317
                        ],
                        [
                            -84.059837,
                            33.734224
                        ],
                        [
                            -84.060034,
                            33.734151
                        ],
                        [
                            -84.061605,
                            33.733489
                        ],
                        [
                            -84.063,
                            33.732839
                        ],
                        [
                            -84.06394,
                            33.73258
                        ],
                        [
                            -84.064142,
                            33.732565
                        ],
                        [
                            -84.064429,
                            33.732552
                        ],
                        [
                            -84.064862,
                            33.732584
                        ],
                        [
                            -84.06515,
                            33.732622
                        ],
                        [
                            -84.065356,
                            33.732644
                        ],
                        [
                            -84.065853,
                            33.732745
                        ],
                        [
                            -84.066484,
                            33.732968
                        ],
                        [
                            -84.067724,
                            33.733474
                        ],
                        [
                            -84.069151,
                            33.734101
                        ],
                        [
                            -84.069594,
                            33.73428
                        ],
                        [
                            -84.070199,
                            33.734555
                        ],
                        [
                            -84.07173,
                            33.735324
                        ],
                        [
                            -84.072093,
                            33.735481
                        ],
                        [
                            -84.072424,
                            33.735509
                        ],
                        [
                            -84.072786,
                            33.735491
                        ],
                        [
                            -84.072968,
                            33.735468
                        ],
                        [
                            -84.073105,
                            33.735434
                        ],
                        [
                            -84.073322,
                            33.735336
                        ],
                        [
                            -84.073508,
                            33.735228
                        ],
                        [
                            -84.074117,
                            33.734796
                        ],
                        [
                            -84.074403,
                            33.734682
                        ],
                        [
                            -84.074601,
                            33.734613
                        ],
                        [
                            -84.074934,
                            33.734555
                        ],
                        [
                            -84.075231,
                            33.734536
                        ],
                        [
                            -84.076007,
                            33.734586
                        ],
                        [
                            -84.077626,
                            33.734658
                        ],
                        [
                            -84.078487,
                            33.734666
                        ],
                        [
                            -84.080123,
                            33.734692
                        ],
                        [
                            -84.081199,
                            33.734692
                        ],
                        [
                            -84.082313,
                            33.734705
                        ],
                        [
                            -84.082993,
                            33.734691
                        ],
                        [
                            -84.084017,
                            33.73473
                        ],
                        [
                            -84.085854,
                            33.734745
                        ],
                        [
                            -84.086746,
                            33.73478
                        ],
                        [
                            -84.087372,
                            33.734725
                        ],
                        [
                            -84.08798,
                            33.734683
                        ],
                        [
                            -84.088744,
                            33.734546
                        ],
                        [
                            -84.087833,
                            33.735567
                        ],
                        [
                            -84.085917,
                            33.737874
                        ],
                        [
                            -84.086508,
                            33.738338
                        ],
                        [
                            -84.086917,
                            33.7387
                        ],
                        [
                            -84.087215,
                            33.738876
                        ],
                        [
                            -84.087482,
                            33.738953
                        ],
                        [
                            -84.087784,
                            33.738988
                        ],
                        [
                            -84.088511,
                            33.738935
                        ],
                        [
                            -84.090448,
                            33.738981
                        ],
                        [
                            -84.092303,
                            33.738968
                        ],
                        [
                            -84.094851,
                            33.738901
                        ],
                        [
                            -84.096136,
                            33.738805
                        ],
                        [
                            -84.097463,
                            33.738588
                        ],
                        [
                            -84.098003,
                            33.73844
                        ],
                        [
                            -84.098384,
                            33.738314
                        ],
                        [
                            -84.098782,
                            33.738093
                        ],
                        [
                            -84.099519,
                            33.737378
                        ],
                        [
                            -84.101206,
                            33.736445
                        ],
                        [
                            -84.101819,
                            33.735769
                        ],
                        [
                            -84.102541,
                            33.734857
                        ],
                        [
                            -84.103134,
                            33.734129
                        ],
                        [
                            -84.103296,
                            33.733945
                        ],
                        [
                            -84.103946,
                            33.733609
                        ],
                        [
                            -84.103977,
                            33.734286
                        ],
                        [
                            -84.103959,
                            33.735066
                        ],
                        [
                            -84.103907,
                            33.735433
                        ],
                        [
                            -84.1037,
                            33.736209
                        ],
                        [
                            -84.103545,
                            33.736612
                        ],
                        [
                            -84.103352,
                            33.736989
                        ],
                        [
                            -84.103173,
                            33.737418
                        ],
                        [
                            -84.102957,
                            33.737747
                        ],
                        [
                            -84.102852,
                            33.738086
                        ],
                        [
                            -84.102769,
                            33.738432
                        ],
                        [
                            -84.102755,
                            33.738865
                        ],
                        [
                            -84.102759,
                            33.739089
                        ],
                        [
                            -84.102752,
                            33.741488
                        ],
                        [
                            -84.102797,
                            33.742038
                        ],
                        [
                            -84.102897,
                            33.742423
                        ],
                        [
                            -84.103049,
                            33.742821
                        ],
                        [
                            -84.103268,
                            33.743225
                        ],
                        [
                            -84.10356,
                            33.743935
                        ],
                        [
                            -84.103732,
                            33.744547
                        ],
                        [
                            -84.10383,
                            33.744739
                        ],
                        [
                            -84.104142,
                            33.745502
                        ],
                        [
                            -84.104287,
                            33.745873
                        ],
                        [
                            -84.104402,
                            33.746184
                        ],
                        [
                            -84.104707,
                            33.746926
                        ],
                        [
                            -84.104904,
                            33.747397
                        ],
                        [
                            -84.105148,
                            33.747829
                        ],
                        [
                            -84.105813,
                            33.748863
                        ],
                        [
                            -84.10606,
                            33.749236
                        ],
                        [
                            -84.106403,
                            33.749814
                        ],
                        [
                            -84.106569,
                            33.750048
                        ],
                        [
                            -84.106661,
                            33.750321
                        ],
                        [
                            -84.106647,
                            33.750573
                        ],
                        [
                            -84.106658,
                            33.751151
                        ],
                        [
                            -84.106643,
                            33.751307
                        ],
                        [
                            -84.106543,
                            33.751698
                        ],
                        [
                            -84.106532,
                            33.752098
                        ],
                        [
                            -84.106475,
                            33.752205
                        ],
                        [
                            -84.1064,
                            33.752297
                        ],
                        [
                            -84.106135,
                            33.752944
                        ],
                        [
                            -84.106118,
                            33.753044
                        ],
                        [
                            -84.106075,
                            33.753742
                        ],
                        [
                            -84.106088,
                            33.753919
                        ],
                        [
                            -84.106114,
                            33.75408
                        ],
                        [
                            -84.106116,
                            33.754165
                        ],
                        [
                            -84.106132,
                            33.754258
                        ],
                        [
                            -84.106158,
                            33.754343
                        ],
                        [
                            -84.106261,
                            33.75449
                        ],
                        [
                            -84.106315,
                            33.754543
                        ],
                        [
                            -84.106376,
                            33.754581
                        ],
                        [
                            -84.106523,
                            33.75465
                        ],
                        [
                            -84.106775,
                            33.754739
                        ],
                        [
                            -84.107021,
                            33.754799
                        ],
                        [
                            -84.107222,
                            33.75488
                        ],
                        [
                            -84.107329,
                            33.754932
                        ],
                        [
                            -84.107525,
                            33.755098
                        ],
                        [
                            -84.107663,
                            33.755286
                        ],
                        [
                            -84.107828,
                            33.755523
                        ],
                        [
                            -84.107932,
                            33.755712
                        ],
                        [
                            -84.107952,
                            33.755773
                        ],
                        [
                            -84.107962,
                            33.755907
                        ],
                        [
                            -84.107937,
                            33.756351
                        ],
                        [
                            -84.107906,
                            33.756627
                        ],
                        [
                            -84.107889,
                            33.756713
                        ],
                        [
                            -84.107891,
                            33.756788
                        ],
                        [
                            -84.10794,
                            33.756985
                        ],
                        [
                            -84.108114,
                            33.757606
                        ],
                        [
                            -84.108182,
                            33.757799
                        ],
                        [
                            -84.108189,
                            33.757877
                        ],
                        [
                            -84.108156,
                            33.75828
                        ],
                        [
                            -84.108208,
                            33.758446
                        ],
                        [
                            -84.108219,
                            33.758834
                        ]
                    ]
                ]
            }
        },
        {
            "type": "Feature",
            "properties": {
                "MOVEMENT_ID": "76",
                "TRACTCE": "021912",
                "GEOID": "13089021912",
                "DISPLAY_NAME": "Census Tract 219.12"
            },
            "geometry": {
                "type": "Polygon",
                "coordinates": [
                    [
                        [
                            -84.184155,
                            33.836613
                        ],
                        [
                            -84.184025,
                            33.836998
                        ],
                        [
                            -84.183827,
                            33.837437
                        ],
                        [
                            -84.183529,
                            33.837765
                        ],
                        [
                            -84.183102,
                            33.838194
                        ],
                        [
                            -84.182888,
                            33.838522
                        ],
                        [
                            -84.182644,
                            33.838674
                        ],
                        [
                            -84.18222,
                            33.838878
                        ],
                        [
                            -84.182237,
                            33.839329
                        ],
                        [
                            -84.18225,
                            33.840446
                        ],
                        [
                            -84.182192,
                            33.8417
                        ],
                        [
                            -84.182211,
                            33.842155
                        ],
                        [
                            -84.182285,
                            33.842392
                        ],
                        [
                            -84.182363,
                            33.842545
                        ],
                        [
                            -84.182599,
                            33.842909
                        ],
                        [
                            -84.182933,
                            33.843531
                        ],
                        [
                            -84.183,
                            33.843702
                        ],
                        [
                            -84.183026,
                            33.84379
                        ],
                        [
                            -84.183046,
                            33.843878
                        ],
                        [
                            -84.18306,
                            33.843968
                        ],
                        [
                            -84.183041,
                            33.844231
                        ],
                        [
                            -84.182892,
                            33.844557
                        ],
                        [
                            -84.182843,
                            33.844651
                        ],
                        [
                            -84.18279,
                            33.84473
                        ],
                        [
                            -84.182729,
                            33.844804
                        ],
                        [
                            -84.182659,
                            33.844873
                        ],
                        [
                            -84.182582,
                            33.844936
                        ],
                        [
                            -84.182327,
                            33.845165
                        ],
                        [
                            -84.18223,
                            33.845311
                        ],
                        [
                            -84.182185,
                            33.845393
                        ],
                        [
                            -84.182145,
                            33.845477
                        ],
                        [
                            -84.182111,
                            33.845563
                        ],
                        [
                            -84.18206,
                            33.845738
                        ],
                        [
                            -84.181941,
                            33.846852
                        ],
                        [
                            -84.181561,
                            33.848347
                        ],
                        [
                            -84.181346,
                            33.848356
                        ],
                        [
                            -84.180461,
                            33.848115
                        ],
                        [
                            -84.180075,
                            33.848027
                        ],
                        [
                            -84.179663,
                            33.847918
                        ],
                        [
                            -84.179257,
                            33.847795
                        ],
                        [
                            -84.178858,
                            33.847659
                        ],
                        [
                            -84.178203,
                            33.847415
                        ],
                        [
                            -84.17593,
                            33.846659
                        ],
                        [
                            -84.173398,
                            33.847195
                        ],
                        [
                            -84.170776,
                            33.847726
                        ],
                        [
                            -84.17059,
                            33.847759
                        ],
                        [
                            -84.170566,
                            33.847759
                        ],
                        [
                            -84.170122,
                            33.847826
                        ],
                        [
                            -84.169822,
                            33.847887
                        ],
                        [
                            -84.169646,
                            33.847936
                        ],
                        [
                            -84.169446,
                            33.848004
                        ],
                        [
                            -84.169251,
                            33.848082
                        ],
                        [
                            -84.169063,
                            33.84817
                        ],
                        [
                            -84.168,
                            33.848642
                        ],
                        [
                            -84.167708,
                            33.848756
                        ],
                        [
                            -84.167259,
                            33.848985
                        ],
                        [
                            -84.166999,
                            33.849091
                        ],
                        [
                            -84.166769,
                            33.849214
                        ],
                        [
                            -84.166622,
                            33.849313
                        ],
                        [
                            -84.166282,
                            33.849648
                        ],
                        [
                            -84.166227,
                            33.849759
                        ],
                        [
                            -84.166182,
                            33.849886
                        ],
                        [
                            -84.16612,
                            33.850202
                        ],
                        [
                            -84.166074,
                            33.850346
                        ],
                        [
                            -84.166037,
                            33.850589
                        ],
                        [
                            -84.165834,
                            33.851695
                        ],
                        [
                            -84.165735,
                            33.852207
                        ],
                        [
                            -84.165697,
                            33.852363
                        ],
                        [
                            -84.165638,
                            33.852536
                        ],
                        [
                            -84.16556,
                            33.852705
                        ],
                        [
                            -84.165466,
                            33.852867
                        ],
                        [
                            -84.165197,
                            33.853257
                        ],
                        [
                            -84.164645,
                            33.853834
                        ],
                        [
                            -84.164062,
                            33.854573
                        ],
                        [
                            -84.163813,
                            33.854982
                        ],
                        [
                            -84.163788,
                            33.85504
                        ],
                        [
                            -84.162894,
                            33.854628
                        ],
                        [
                            -84.161377,
                            33.853973
                        ],
                        [
                            -84.161109,
                            33.853892
                        ],
                        [
                            -84.161022,
                            33.853894
                        ],
                        [
                            -84.157817,
                            33.853204
                        ],
                        [
                            -84.156617,
                            33.852304
                        ],
                        [
                            -84.154517,
                            33.850104
                        ],
                        [
                            -84.150562,
                            33.846053
                        ],
                        [
                            -84.148337,
                            33.842564
                        ],
                        [
                            -84.144841,
                            33.840328
                        ],
                        [
                            -84.14461,
                            33.840157
                        ],
                        [
                            -84.141216,
                            33.839004
                        ],
                        [
                            -84.139916,
                            33.838404
                        ],
                        [
                            -84.13898,
                            33.837862
                        ],
                        [
                            -84.138311,
                            33.837211
                        ],
                        [
                            -84.134852,
                            33.835256
                        ],
                        [
                            -84.134257,
                            33.834467
                        ],
                        [
                            -84.134015,
                            33.834102
                        ],
                        [
                            -84.132716,
                            33.830505
                        ],
                        [
                            -84.127916,
                            33.825305
                        ],
                        [
                            -84.126916,
                            33.823805
                        ],
                        [
                            -84.126335,
                            33.823139
                        ],
                        [
                            -84.126257,
                            33.82305
                        ],
                        [
                            -84.126216,
                            33.823006
                        ],
                        [
                            -84.126103,
                            33.82287
                        ],
                        [
                            -84.127187,
                            33.822919
                        ],
                        [
                            -84.127875,
                            33.822978
                        ],
                        [
                            -84.129133,
                            33.823175
                        ],
                        [
                            -84.129943,
                            33.823254
                        ],
                        [
                            -84.130744,
                            33.823373
                        ],
                        [
                            -84.131328,
                            33.823501
                        ],
                        [
                            -84.132256,
                            33.823785
                        ],
                        [
                            -84.133025,
                            33.823974
                        ],
                        [
                            -84.133605,
                            33.824069
                        ],
                        [
                            -84.133912,
                            33.824104
                        ],
                        [
                            -84.134293,
                            33.824138
                        ],
                        [
                            -84.134919,
                            33.824125
                        ],
                        [
                            -84.135332,
                            33.824072
                        ],
                        [
                            -84.135742,
                            33.824028
                        ],
                        [
                            -84.136186,
                            33.82393
                        ],
                        [
                            -84.136639,
                            33.823833
                        ],
                        [
                            -84.137429,
                            33.823712
                        ],
                        [
                            -84.138033,
                            33.823668
                        ],
                        [
                            -84.138512,
                            33.823649
                        ],
                        [
                            -84.139043,
                            33.823666
                        ],
                        [
                            -84.13988,
                            33.82368
                        ],
                        [
                            -84.139995,
                            33.82368
                        ],
                        [
                            -84.141875,
                            33.823761
                        ],
                        [
                            -84.143919,
                            33.823891
                        ],
                        [
                            -84.145533,
                            33.823957
                        ],
                        [
                            -84.14573,
                            33.823983
                        ],
                        [
                            -84.146097,
                            33.823996
                        ],
                        [
                            -84.146747,
                            33.824035
                        ],
                        [
                            -84.149015,
                            33.824152
                        ],
                        [
                            -84.149321,
                            33.824156
                        ],
                        [
                            -84.152235,
                            33.824101
                        ],
                        [
                            -84.152473,
                            33.824093
                        ],
                        [
                            -84.15368,
                            33.823941
                        ],
                        [
                            -84.154401,
                            33.823845
                        ],
                        [
                            -84.155992,
                            33.823586
                        ],
                        [
                            -84.159088,
                            33.822826
                        ],
                        [
                            -84.159742,
                            33.82259
                        ],
                        [
                            -84.160757,
                            33.82223
                        ],
                        [
                            -84.162723,
                            33.821592
                        ],
                        [
                            -84.163579,
                            33.82131
                        ],
                        [
                            -84.164538,
                            33.821082
                        ],
                        [
                            -84.16528,
                            33.820871
                        ],
                        [
                            -84.165696,
                            33.820713
                        ],
                        [
                            -84.166261,
                            33.820638
                        ],
                        [
                            -84.167151,
                            33.820609
                        ],
                        [
                            -84.167899,
                            33.820656
                        ],
                        [
                            -84.168969,
                            33.82093
                        ],
                        [
                            -84.169747,
                            33.82116
                        ],
                        [
                            -84.170505,
                            33.821504
                        ],
                        [
                            -84.171073,
                            33.821852
                        ],
                        [
                            -84.171509,
                            33.822159
                        ],
                        [
                            -84.171876,
                            33.822513
                        ],
                        [
                            -84.173177,
                            33.824143
                        ],
                        [
                            -84.173459,
                            33.824476
                        ],
                        [
                            -84.173717,
                            33.824798
                        ],
                        [
                            -84.173891,
                            33.825026
                        ],
                        [
                            -84.174078,
                            33.825246
                        ],
                        [
                            -84.174279,
                            33.825459
                        ],
                        [
                            -84.174896,
                            33.826086
                        ],
                        [
                            -84.175526,
                            33.826703
                        ],
                        [
                            -84.176222,
                            33.827357
                        ],
                        [
                            -84.177042,
                            33.828038
                        ],
                        [
                            -84.177902,
                            33.828619
                        ],
                        [
                            -84.178146,
                            33.828863
                        ],
                        [
                            -84.17812,
                            33.829424
                        ],
                        [
                            -84.178095,
                            33.82981
                        ],
                        [
                            -84.178057,
                            33.829986
                        ],
                        [
                            -84.178003,
                            33.830161
                        ],
                        [
                            -84.177933,
                            33.830331
                        ],
                        [
                            -84.177849,
                            33.830497
                        ],
                        [
                            -84.177724,
                            33.830709
                        ],
                        [
                            -84.176923,
                            33.831684
                        ],
                        [
                            -84.177746,
                            33.833293
                        ],
                        [
                            -84.178026,
                            33.833175
                        ],
                        [
                            -84.178339,
                            33.833148
                        ],
                        [
                            -84.178865,
                            33.833118
                        ],
                        [
                            -84.179461,
                            33.833134
                        ],
                        [
                            -84.18014,
                            33.833408
                        ],
                        [
                            -84.180483,
                            33.833433
                        ],
                        [
                            -84.18088,
                            33.833365
                        ],
                        [
                            -84.181383,
                            33.833308
                        ],
                        [
                            -84.181948,
                            33.833324
                        ],
                        [
                            -84.182306,
                            33.833404
                        ],
                        [
                            -84.182673,
                            33.83379
                        ],
                        [
                            -84.182818,
                            33.833968
                        ],
                        [
                            -84.183085,
                            33.834313
                        ],
                        [
                            -84.183672,
                            33.834777
                        ],
                        [
                            -84.183978,
                            33.83497
                        ],
                        [
                            -84.184124,
                            33.835582
                        ],
                        [
                            -84.184208,
                            33.83609
                        ],
                        [
                            -84.184155,
                            33.836613
                        ]
                    ]
                ]
            }
        }
    ]
}